main.py
uv_dependencie_demo-0.1.1.dist-info/METADATA
uv_dependencie_demo-0.1.1.dist-info/WHEEL
uv_dependencie_demo-0.1.1.dist-info/top_level.txt
uv_dependencie_demo-0.1.1.dist-info/RECORD
