Metadata-Version: 2.4
Name: uv-dependencie-demo
Version: 0.1.1
Summary: Add your description here
Requires-Python: >=3.12
Requires-Dist: fastapi>=0.115.12
Requires-Dist: unicorn>=2.1.3
Requires-Dist: twine>=6.1.0
Requires-Dist: uvicorn>=0.34.3
